examples/diff_example.py
examples/dsl_example.py
examples/example.py
examples/exampleResume.py
examples/example_account.py
examples/example_action_log.py
examples/example_client.py
examples/example_mcp_anthropic.py
examples/example_mcp_openai.py
examples/example_sync.py
examples/example_task.py
examples/example_tasks.py
examples/example_verifier.py
examples/export_tasks.py
examples/export_tasks_filtered.py
examples/fetch_tasks.py
examples/gemini_example.py
examples/import_tasks.py
examples/iterate_verifiers.py
examples/json_tasks_example.py
examples/nova_act_example.py
examples/openai_example.py
examples/openai_simple_example.py
examples/query_builder_example.py
examples/quickstart.py
examples/test_cdp_logging.py
fleet/__init__.py
fleet/base.py
fleet/cli.py
fleet/client.py
fleet/config.py
fleet/exceptions.py
fleet/global_client.py
fleet/models.py
fleet/tasks.py
fleet/types.py
fleet/_async/__init__.py
fleet/_async/base.py
fleet/_async/client.py
fleet/_async/exceptions.py
fleet/_async/global_client.py
fleet/_async/models.py
fleet/_async/tasks.py
fleet/_async/env/__init__.py
fleet/_async/env/client.py
fleet/_async/instance/__init__.py
fleet/_async/instance/base.py
fleet/_async/instance/client.py
fleet/_async/resources/__init__.py
fleet/_async/resources/api.py
fleet/_async/resources/base.py
fleet/_async/resources/browser.py
fleet/_async/resources/mcp.py
fleet/_async/resources/sqlite.py
fleet/_async/verifiers/__init__.py
fleet/_async/verifiers/bundler.py
fleet/_async/verifiers/verifier.py
fleet/agent/__init__.py
fleet/agent/orchestrator.py
fleet/agent/types.py
fleet/agent/utils.py
fleet/agent/gemini_cua/Dockerfile
fleet/agent/gemini_cua/__init__.py
fleet/agent/gemini_cua/agent.py
fleet/agent/gemini_cua/requirements.txt
fleet/agent/gemini_cua/start.sh
fleet/agent/gemini_cua/mcp/main.py
fleet/agent/gemini_cua/mcp_server/__init__.py
fleet/agent/gemini_cua/mcp_server/main.py
fleet/agent/gemini_cua/mcp_server/tools.py
fleet/env/__init__.py
fleet/env/client.py
fleet_python-0.2.103.dist-info/licenses/LICENSE
fleet_python-0.2.103.dist-info/METADATA
fleet_python-0.2.103.dist-info/WHEEL
fleet_python-0.2.103.dist-info/entry_points.txt
fleet_python-0.2.103.dist-info/top_level.txt
fleet_python-0.2.103.dist-info/RECORD
