Metadata-Version: 2.4
Name: fleet-python
Version: 0.2.103
Summary: Python SDK for Fleet environments
Author-email: Fleet AI <nic@fleet.so>
License: Apache-2.0
Project-URL: Homepage, https://fleetai.com
Project-URL: Documentation, https://docs.fleetai.com
Project-URL: Repository, https://github.com/fleet-ai/fleet-sdk
Project-URL: Issues, https://github.com/fleet-ai/fleet-sdk/issues
Classifier: Development Status :: 3 - Alpha
Classifier: Intended Audience :: Developers
Classifier: License :: OSI Approved :: Apache Software License
Classifier: Programming Language :: Python :: 3
Classifier: Programming Language :: Python :: 3.9
Classifier: Programming Language :: Python :: 3.10
Classifier: Programming Language :: Python :: 3.11
Classifier: Programming Language :: Python :: 3.12
Requires-Python: >=3.9
License-File: LICENSE
Requires-Dist: aiohttp>=3.8.0
Requires-Dist: pydantic>=2.0.0
Requires-Dist: httpx>=0.27.0
Requires-Dist: httpx-retries>=0.4.0
Requires-Dist: typing-extensions>=4.0.0
Requires-Dist: modulegraph2>=0.2.0
Requires-Dist: cloudpickle==3.1.1
Provides-Extra: cli
Requires-Dist: typer>=0.9.0; extra == "cli"
Requires-Dist: rich>=10.0.0; extra == "cli"
Provides-Extra: dev
Requires-Dist: pytest>=7.0.0; extra == "dev"
Requires-Dist: pytest-asyncio>=0.21.0; extra == "dev"
Requires-Dist: black>=22.0.0; extra == "dev"
Requires-Dist: isort>=5.0.0; extra == "dev"
Requires-Dist: mypy>=1.0.0; extra == "dev"
Requires-Dist: ruff>=0.1.0; extra == "dev"
Requires-Dist: unasync>=0.6.0; extra == "dev"
Requires-Dist: python-dotenv>=1.1.1; extra == "dev"
Requires-Dist: typer>=0.9.0; extra == "dev"
Requires-Dist: rich>=10.0.0; extra == "dev"
Provides-Extra: playwright
Requires-Dist: playwright>=1.40.0; extra == "playwright"
Provides-Extra: eval
Requires-Dist: aiohttp>=3.9.0; extra == "eval"
Requires-Dist: google-genai>=1.0.0; extra == "eval"
Requires-Dist: mcp==1.24.0; python_version >= "3.10" and extra == "eval"
Dynamic: license-file
